hypothesmith/__init__.py
hypothesmith/cst.py
hypothesmith/py.typed
hypothesmith/python.lark
hypothesmith/syntactic.py
hypothesmith-0.3.3.dist-info/LICENSE
hypothesmith-0.3.3.dist-info/METADATA
hypothesmith-0.3.3.dist-info/WHEEL
hypothesmith-0.3.3.dist-info/top_level.txt
hypothesmith-0.3.3.dist-info/RECORD
