Metadata-Version: 2.1
Name: hypothesmith
Version: 0.3.3
Summary: Hypothesis strategies for generating Python programs, something like CSmith
Home-page: https://github.com/Zac-HD/hypothesmith
Author: Zac Hatfield-Dodds
Author-email: zac@hypothesis.works
License: MPL 2.0
Project-URL: Funding, https://github.com/sponsors/Zac-HD
Keywords: python testing fuzzing property-based-testing
Classifier: Development Status :: 4 - Beta
Classifier: Framework :: Hypothesis
Classifier: Intended Audience :: Developers
Classifier: License :: OSI Approved :: Mozilla Public License 2.0 (MPL 2.0)
Classifier: Programming Language :: Python
Classifier: Programming Language :: Python :: 3
Classifier: Programming Language :: Python :: 3.8
Classifier: Programming Language :: Python :: 3.9
Classifier: Programming Language :: Python :: 3.10
Classifier: Programming Language :: Python :: 3.11
Classifier: Programming Language :: Python :: 3.12
Classifier: Topic :: Software Development :: Testing
Requires-Python: >=3.8
License-File: LICENSE
Requires-Dist: hypothesis[lark] >=6.93.0
Requires-Dist: libcst >=1.0.1
